UQpy/__init__.py
UQpy/dimension_reduction/__init__.py
UQpy/dimension_reduction/diffusion_maps/DiffusionMaps.py
UQpy/dimension_reduction/diffusion_maps/__init__.py
UQpy/dimension_reduction/grassmann_manifold/GrassmannInterpolation.py
UQpy/dimension_reduction/grassmann_manifold/GrassmannOperations.py
UQpy/dimension_reduction/grassmann_manifold/__init__.py
UQpy/dimension_reduction/grassmann_manifold/projections/SVDProjection.py
UQpy/dimension_reduction/grassmann_manifold/projections/__init__.py
UQpy/dimension_reduction/grassmann_manifold/projections/baseclass/GrassmannProjection.py
UQpy/dimension_reduction/grassmann_manifold/projections/baseclass/__init__.py
UQpy/dimension_reduction/hosvd/HigherOrderSVD.py
UQpy/dimension_reduction/hosvd/__init__.py
UQpy/dimension_reduction/pod/DirectPOD.py
UQpy/dimension_reduction/pod/SnapshotPOD.py
UQpy/dimension_reduction/pod/__init__.py
UQpy/dimension_reduction/pod/baseclass/POD.py
UQpy/dimension_reduction/pod/baseclass/__init__.py
UQpy/distributions/__init__.py
UQpy/distributions/baseclass/Copula.py
UQpy/distributions/baseclass/Distribution.py
UQpy/distributions/baseclass/Distribution1D.py
UQpy/distributions/baseclass/DistributionContinuous1D.py
UQpy/distributions/baseclass/DistributionDiscrete1D.py
UQpy/distributions/baseclass/DistributionND.py
UQpy/distributions/baseclass/__init__.py
UQpy/distributions/collection/Beta.py
UQpy/distributions/collection/Binomial.py
UQpy/distributions/collection/Cauchy.py
UQpy/distributions/collection/ChiSquare.py
UQpy/distributions/collection/Exponential.py
UQpy/distributions/collection/Gamma.py
UQpy/distributions/collection/GeneralizedExtreme.py
UQpy/distributions/collection/InverseGaussian.py
UQpy/distributions/collection/JointCopula.py
UQpy/distributions/collection/JointIndependent.py
UQpy/distributions/collection/Laplace.py
UQpy/distributions/collection/Levy.py
UQpy/distributions/collection/Logistic.py
UQpy/distributions/collection/Lognormal.py
UQpy/distributions/collection/Maxwell.py
test_uqpy-4.0.1.dist-info/LICENSE
test_uqpy-4.0.1.dist-info/METADATA
test_uqpy-4.0.1.dist-info/WHEEL
test_uqpy-4.0.1.dist-info/top_level.txt
test_uqpy-4.0.1.dist-info/RECORD
